Metadata-Version: 2.1
Name: term-chatgpt
Version: 1.1.5
Summary: Ask ChatGPT directly on your terminal! Fast & Free.
Author: AWeirdDev
Author-email: aweirdscratcher@gmail.com
License: MIT License
Keywords: chatgpt,gpt,free,terminal,textual,rich,chat-gpt,ai
Classifier: Programming Language :: Python :: 3.10
Classifier: License :: OSI Approved :: MIT License
Classifier: Operating System :: OS Independent
Classifier: Environment :: Console
License-File: LICENSE
